{"model":"EOT20","version":"EOT20","manifestHash":"379f1d47e81615d2cd226f1181594a047ecccd9c716f9e82408dc097e518b869","calculationCoordinates":{"latitude":-33.55,"longitude":151.22},"applicability":"LOW_CONFIDENCE","confidence":0.42,"cacheHit":false,"values":[{"timestampUtc":"2026-07-12T03:00:00Z","heightM":-0.3650682270526886,"phase":"slack","changeMPerHour":0},{"timestampUtc":"2026-07-12T03:30:00Z","heightM":-0.25801074504852295,"phase":"rising","changeMPerHour":0.2141},{"timestampUtc":"2026-07-12T04:00:00Z","heightM":-0.12496892362833023,"phase":"rising","changeMPerHour":0.2661},{"timestampUtc":"2026-07-12T04:30:00Z","heightM":0.028046660125255585,"phase":"rising","changeMPerHour":0.306},{"timestampUtc":"2026-07-12T05:00:00Z","heightM":0.19349651038646698,"phase":"rising","changeMPerHour":0.3309},{"timestampUtc":"2026-07-12T05:30:00Z","heightM":0.3626157343387604,"phase":"rising","changeMPerHour":0.3382},{"timestampUtc":"2026-07-12T06:00:00Z","heightM":0.5258587598800659,"phase":"rising","changeMPerHour":0.3265},{"timestampUtc":"2026-07-12T06:30:00Z","heightM":0.6734786033630371,"phase":"rising","changeMPerHour":0.2952},{"timestampUtc":"2026-07-12T07:00:00Z","heightM":0.7962048649787903,"phase":"rising","changeMPerHour":0.2455},{"timestampUtc":"2026-07-12T07:30:00Z","heightM":0.8859590291976929,"phase":"rising","changeMPerHour":0.1795},{"timestampUtc":"2026-07-12T08:00:00Z","heightM":0.936526894569397,"phase":"rising","changeMPerHour":0.1011},{"timestampUtc":"2026-07-12T08:30:00Z","heightM":0.9441043138504028,"phase":"rising","changeMPerHour":0.0152},{"timestampUtc":"2026-07-12T09:00:00Z","heightM":0.9076446890830994,"phase":"falling","changeMPerHour":-0.0729},{"timestampUtc":"2026-07-12T09:30:00Z","heightM":0.8289600610733032,"phase":"falling","changeMPerHour":-0.1574},{"timestampUtc":"2026-07-12T10:00:00Z","heightM":0.7125650644302368,"phase":"falling","changeMPerHour":-0.2328},{"timestampUtc":"2026-07-12T10:30:00Z","heightM":0.5652866363525391,"phase":"falling","changeMPerHour":-0.2946},{"timestampUtc":"2026-07-12T11:00:00Z","heightM":0.3956967890262604,"phase":"falling","changeMPerHour":-0.3392},{"timestampUtc":"2026-07-12T11:30:00Z","heightM":0.2134421318769455,"phase":"falling","changeMPerHour":-0.3645},{"timestampUtc":"2026-07-12T12:00:00Z","heightM":0.028552234172821045,"phase":"falling","changeMPerHour":-0.3698},{"timestampUtc":"2026-07-12T12:30:00Z","heightM":-0.1492033451795578,"phase":"falling","changeMPerHour":-0.3555},{"timestampUtc":"2026-07-12T13:00:00Z","heightM":-0.3108598589897156,"phase":"falling","changeMPerHour":-0.3233},{"timestampUtc":"2026-07-12T13:30:00Z","heightM":-0.44868117570877075,"phase":"falling","changeMPerHour":-0.2756},{"timestampUtc":"2026-07-12T14:00:00Z","heightM":-0.5564647912979126,"phase":"falling","changeMPerHour":-0.2156},{"timestampUtc":"2026-07-12T14:30:00Z","heightM":-0.6297491192817688,"phase":"falling","changeMPerHour":-0.1466},{"timestampUtc":"2026-07-12T15:00:00Z","heightM":-0.6659493446350098,"phase":"falling","changeMPerHour":-0.0724},{"timestampUtc":"2026-07-12T15:30:00Z","heightM":-0.664444625377655,"phase":"slack","changeMPerHour":0.003},{"timestampUtc":"2026-07-12T16:00:00Z","heightM":-0.6266237497329712,"phase":"rising","changeMPerHour":0.0756},{"timestampUtc":"2026-07-12T16:30:00Z","heightM":-0.5558801889419556,"phase":"rising","changeMPerHour":0.1415},{"timestampUtc":"2026-07-12T17:00:00Z","heightM":-0.4575299024581909,"phase":"rising","changeMPerHour":0.1967},{"timestampUtc":"2026-07-12T17:30:00Z","heightM":-0.33861979842185974,"phase":"rising","changeMPerHour":0.2378},{"timestampUtc":"2026-07-12T18:00:00Z","heightM":-0.20759740471839905,"phase":"rising","changeMPerHour":0.262},{"timestampUtc":"2026-07-12T18:30:00Z","heightM":-0.07382920384407043,"phase":"rising","changeMPerHour":0.2675},{"timestampUtc":"2026-07-12T19:00:00Z","heightM":0.053018853068351746,"phase":"rising","changeMPerHour":0.2537},{"timestampUtc":"2026-07-12T19:30:00Z","heightM":0.16369731724262238,"phase":"rising","changeMPerHour":0.2214},{"timestampUtc":"2026-07-12T20:00:00Z","heightM":0.2501174807548523,"phase":"rising","changeMPerHour":0.1728},{"timestampUtc":"2026-07-12T20:30:00Z","heightM":0.3060401380062103,"phase":"rising","changeMPerHour":0.1118},{"timestampUtc":"2026-07-12T21:00:00Z","heightM":0.3276238441467285,"phase":"rising","changeMPerHour":0.0432},{"timestampUtc":"2026-07-12T21:30:00Z","heightM":0.31376126408576965,"phase":"falling","changeMPerHour":-0.0277},{"timestampUtc":"2026-07-12T22:00:00Z","heightM":0.2661604881286621,"phase":"falling","changeMPerHour":-0.0952},{"timestampUtc":"2026-07-12T22:30:00Z","heightM":0.18916359543800354,"phase":"falling","changeMPerHour":-0.154},{"timestampUtc":"2026-07-12T23:00:00Z","heightM":0.08933199942111969,"phase":"falling","changeMPerHour":-0.1997},{"timestampUtc":"2026-07-12T23:30:00Z","heightM":-0.025141965597867966,"phase":"falling","changeMPerHour":-0.2289},{"timestampUtc":"2026-07-13T00:00:00Z","heightM":-0.1451190561056137,"phase":"falling","changeMPerHour":-0.24},{"timestampUtc":"2026-07-13T00:30:00Z","heightM":-0.26121193170547485,"phase":"falling","changeMPerHour":-0.2322},{"timestampUtc":"2026-07-13T01:00:00Z","heightM":-0.36442914605140686,"phase":"falling","changeMPerHour":-0.2064},{"timestampUtc":"2026-07-13T01:30:00Z","heightM":-0.44671759009361267,"phase":"falling","changeMPerHour":-0.1646},{"timestampUtc":"2026-07-13T02:00:00Z","heightM":-0.501382052898407,"phase":"falling","changeMPerHour":-0.1093},{"timestampUtc":"2026-07-13T02:30:00Z","heightM":-0.5233868360519409,"phase":"falling","changeMPerHour":-0.044},{"timestampUtc":"2026-07-13T03:00:00Z","heightM":-0.5095586180686951,"phase":"rising","changeMPerHour":0.0277},{"timestampUtc":"2026-07-13T03:30:00Z","heightM":-0.4587172269821167,"phase":"rising","changeMPerHour":0.1017},{"timestampUtc":"2026-07-13T04:00:00Z","heightM":-0.37175196409225464,"phase":"rising","changeMPerHour":0.1739},{"timestampUtc":"2026-07-13T04:30:00Z","heightM":-0.25164881348609924,"phase":"rising","changeMPerHour":0.2402},{"timestampUtc":"2026-07-13T05:00:00Z","heightM":-0.10345534980297089,"phase":"rising","changeMPerHour":0.2964},{"timestampUtc":"2026-07-13T05:30:00Z","heightM":0.06584454327821732,"phase":"rising","changeMPerHour":0.3386},{"timestampUtc":"2026-07-13T06:00:00Z","heightM":0.24757739901542664,"phase":"rising","changeMPerHour":0.3635},{"timestampUtc":"2026-07-13T06:30:00Z","heightM":0.43177464604377747,"phase":"rising","changeMPerHour":0.3684},{"timestampUtc":"2026-07-13T07:00:00Z","heightM":0.6077218055725098,"phase":"rising","changeMPerHour":0.3519},{"timestampUtc":"2026-07-13T07:30:00Z","heightM":0.7646426558494568,"phase":"rising","changeMPerHour":0.3138},{"timestampUtc":"2026-07-13T08:00:00Z","heightM":0.8924695253372192,"phase":"rising","changeMPerHour":0.2557},{"timestampUtc":"2026-07-13T08:30:00Z","heightM":0.9826259613037109,"phase":"rising","changeMPerHour":0.1803},{"timestampUtc":"2026-07-13T09:00:00Z","heightM":1.0287349224090576,"phase":"rising","changeMPerHour":0.0922},{"timestampUtc":"2026-07-13T09:30:00Z","heightM":1.027165412902832,"phase":"slack","changeMPerHour":-0.0031},{"timestampUtc":"2026-07-13T10:00:00Z","heightM":0.977349579334259,"phase":"falling","changeMPerHour":-0.0996},{"timestampUtc":"2026-07-13T10:30:00Z","heightM":0.8818299770355225,"phase":"falling","changeMPerHour":-0.191},{"timestampUtc":"2026-07-13T11:00:00Z","heightM":0.7460350394248962,"phase":"falling","changeMPerHour":-0.2716},{"timestampUtc":"2026-07-13T11:30:00Z","heightM":0.5778181552886963,"phase":"falling","changeMPerHour":-0.3364},{"timestampUtc":"2026-07-13T12:00:00Z","heightM":0.3868231177330017,"phase":"falling","changeMPerHour":-0.382},{"timestampUtc":"2026-07-13T12:30:00Z","heightM":0.18375781178474426,"phase":"falling","changeMPerHour":-0.4061},{"timestampUtc":"2026-07-13T13:00:00Z","heightM":-0.020343303680419922,"phase":"falling","changeMPerHour":-0.4082},{"timestampUtc":"2026-07-13T13:30:00Z","heightM":-0.2147986739873886,"phase":"falling","changeMPerHour":-0.3889},{"timestampUtc":"2026-07-13T14:00:00Z","heightM":-0.389856219291687,"phase":"falling","changeMPerHour":-0.3501},{"timestampUtc":"2026-07-13T14:30:00Z","heightM":-0.5371479988098145,"phase":"falling","changeMPerHour":-0.2946},{"timestampUtc":"2026-07-13T15:00:00Z","heightM":-0.6500279903411865,"phase":"falling","changeMPerHour":-0.2258},{"timestampUtc":"2026-07-13T15:30:00Z","heightM":-0.7238121032714844,"phase":"falling","changeMPerHour":-0.1476},{"timestampUtc":"2026-07-13T16:00:00Z","heightM":-0.755944013595581,"phase":"falling","changeMPerHour":-0.0643},{"timestampUtc":"2026-07-13T16:30:00Z","heightM":-0.7461023926734924,"phase":"rising","changeMPerHour":0.0197},{"timestampUtc":"2026-07-13T17:00:00Z","heightM":-0.6962487101554871,"phase":"rising","changeMPerHour":0.0997},{"timestampUtc":"2026-07-13T17:30:00Z","heightM":-0.6106012463569641,"phase":"rising","changeMPerHour":0.1713},{"timestampUtc":"2026-07-13T18:00:00Z","heightM":-0.4955044090747833,"phase":"rising","changeMPerHour":0.2302},{"timestampUtc":"2026-07-13T18:30:00Z","heightM":-0.3591632544994354,"phase":"rising","changeMPerHour":0.2727},{"timestampUtc":"2026-07-13T19:00:00Z","heightM":-0.21121959388256073,"phase":"rising","changeMPerHour":0.2959},{"timestampUtc":"2026-07-13T19:30:00Z","heightM":-0.06216806545853615,"phase":"rising","changeMPerHour":0.2981},{"timestampUtc":"2026-07-13T20:00:00Z","heightM":0.07736218720674515,"phase":"rising","changeMPerHour":0.2791},{"timestampUtc":"2026-07-13T20:30:00Z","heightM":0.1974051147699356,"phase":"rising","changeMPerHour":0.2401},{"timestampUtc":"2026-07-13T21:00:00Z","heightM":0.2894563376903534,"phase":"rising","changeMPerHour":0.1841},{"timestampUtc":"2026-07-13T21:30:00Z","heightM":0.34718286991119385,"phase":"rising","changeMPerHour":0.1155},{"timestampUtc":"2026-07-13T22:00:00Z","heightM":0.36695781350135803,"phase":"rising","changeMPerHour":0.0395},{"timestampUtc":"2026-07-13T22:30:00Z","heightM":0.3481537997722626,"phase":"falling","changeMPerHour":-0.0376},{"timestampUtc":"2026-07-13T23:00:00Z","heightM":0.293160617351532,"phase":"falling","changeMPerHour":-0.11},{"timestampUtc":"2026-07-13T23:30:00Z","heightM":0.20713020861148834,"phase":"falling","changeMPerHour":-0.1721},{"timestampUtc":"2026-07-14T00:00:00Z","heightM":0.0974891409277916,"phase":"falling","changeMPerHour":-0.2193},{"timestampUtc":"2026-07-14T00:30:00Z","heightM":-0.02671349048614502,"phase":"falling","changeMPerHour":-0.2484},{"timestampUtc":"2026-07-14T01:00:00Z","heightM":-0.15554030239582062,"phase":"falling","changeMPerHour":-0.2577},{"timestampUtc":"2026-07-14T01:30:00Z","heightM":-0.2789006531238556,"phase":"falling","changeMPerHour":-0.2467},{"timestampUtc":"2026-07-14T02:00:00Z","heightM":-0.3872198760509491,"phase":"falling","changeMPerHour":-0.2166},{"timestampUtc":"2026-07-14T02:30:00Z","heightM":-0.4720001816749573,"phase":"falling","changeMPerHour":-0.1696},{"timestampUtc":"2026-07-14T03:00:00Z","heightM":-0.5262575149536133,"phase":"falling","changeMPerHour":-0.1085},{"timestampUtc":"2026-07-14T03:30:00Z","heightM":-0.5448406338691711,"phase":"falling","changeMPerHour":-0.0372},{"timestampUtc":"2026-07-14T04:00:00Z","heightM":-0.5246524810791016,"phase":"rising","changeMPerHour":0.0404},{"timestampUtc":"2026-07-14T04:30:00Z","heightM":-0.4647955000400543,"phase":"rising","changeMPerHour":0.1197},{"timestampUtc":"2026-07-14T05:00:00Z","heightM":-0.3666544556617737,"phase":"rising","changeMPerHour":0.1963},{"timestampUtc":"2026-07-14T05:30:00Z","heightM":-0.2339133620262146,"phase":"rising","changeMPerHour":0.2655},{"timestampUtc":"2026-07-14T06:00:00Z","heightM":-0.07248920947313309,"phase":"rising","changeMPerHour":0.3228},{"timestampUtc":"2026-07-14T06:30:00Z","heightM":0.10964762419462204,"phase":"rising","changeMPerHour":0.3643},{"timestampUtc":"2026-07-14T07:00:00Z","heightM":0.30279576778411865,"phase":"rising","changeMPerHour":0.3863},{"timestampUtc":"2026-07-14T07:30:00Z","heightM":0.49600717425346375,"phase":"rising","changeMPerHour":0.3864},{"timestampUtc":"2026-07-14T08:00:00Z","heightM":0.6777292490005493,"phase":"rising","changeMPerHour":0.3634},{"timestampUtc":"2026-07-14T08:30:00Z","heightM":0.8365735411643982,"phase":"rising","changeMPerHour":0.3177},{"timestampUtc":"2026-07-14T09:00:00Z","heightM":0.9621485471725464,"phase":"rising","changeMPerHour":0.2512},{"timestampUtc":"2026-07-14T09:30:00Z","heightM":1.0458760261535645,"phase":"rising","changeMPerHour":0.1675},{"timestampUtc":"2026-07-14T10:00:00Z","heightM":1.0816965103149414,"phase":"rising","changeMPerHour":0.0716},{"timestampUtc":"2026-07-14T10:30:00Z","heightM":1.0665820837020874,"phase":"falling","changeMPerHour":-0.0302},{"timestampUtc":"2026-07-14T11:00:00Z","heightM":1.0007908344268799,"phase":"falling","changeMPerHour":-0.1316},{"timestampUtc":"2026-07-14T11:30:00Z","heightM":0.8878353238105774,"phase":"falling","changeMPerHour":-0.2259},{"timestampUtc":"2026-07-14T12:00:00Z","heightM":0.7341750264167786,"phase":"falling","changeMPerHour":-0.3073},{"timestampUtc":"2026-07-14T12:30:00Z","heightM":0.5486766695976257,"phase":"falling","changeMPerHour":-0.371},{"timestampUtc":"2026-07-14T13:00:00Z","heightM":0.3419165015220642,"phase":"falling","changeMPerHour":-0.4135},{"timestampUtc":"2026-07-14T13:30:00Z","heightM":0.1254071742296219,"phase":"falling","changeMPerHour":-0.433},{"timestampUtc":"2026-07-14T14:00:00Z","heightM":-0.0891682580113411,"phase":"falling","changeMPerHour":-0.4292},{"timestampUtc":"2026-07-14T14:30:00Z","heightM":-0.2906510829925537,"phase":"falling","changeMPerHour":-0.403},{"timestampUtc":"2026-07-14T15:00:00Z","heightM":-0.4689905643463135,"phase":"falling","changeMPerHour":-0.3567},{"timestampUtc":"2026-07-14T15:30:00Z","heightM":-0.6157026290893555,"phase":"falling","changeMPerHour":-0.2934},{"timestampUtc":"2026-07-14T16:00:00Z","heightM":-0.7242119312286377,"phase":"falling","changeMPerHour":-0.217},{"timestampUtc":"2026-07-14T16:30:00Z","heightM":-0.7900963425636292,"phase":"falling","changeMPerHour":-0.1318},{"timestampUtc":"2026-07-14T17:00:00Z","heightM":-0.8112548589706421,"phase":"falling","changeMPerHour":-0.0423},{"timestampUtc":"2026-07-14T17:30:00Z","heightM":-0.7880076766014099,"phase":"rising","changeMPerHour":0.0465},{"timestampUtc":"2026-07-14T18:00:00Z","heightM":-0.7231242060661316,"phase":"rising","changeMPerHour":0.1298},{"timestampUtc":"2026-07-14T18:30:00Z","heightM":-0.6217573285102844,"phase":"rising","changeMPerHour":0.2027},{"timestampUtc":"2026-07-14T19:00:00Z","heightM":-0.4912542700767517,"phase":"rising","changeMPerHour":0.261},{"timestampUtc":"2026-07-14T19:30:00Z","heightM":-0.3408152163028717,"phase":"rising","changeMPerHour":0.3009},{"timestampUtc":"2026-07-14T20:00:00Z","heightM":-0.18098480999469757,"phase":"rising","changeMPerHour":0.3197},{"timestampUtc":"2026-07-14T20:30:00Z","heightM":-0.022984478622674942,"phase":"rising","changeMPerHour":0.316},{"timestampUtc":"2026-07-14T21:00:00Z","heightM":0.12207610160112381,"phase":"rising","changeMPerHour":0.2901},{"timestampUtc":"2026-07-14T21:30:00Z","heightM":0.24404273927211761,"phase":"rising","changeMPerHour":0.2439},{"timestampUtc":"2026-07-14T22:00:00Z","heightM":0.33452993631362915,"phase":"rising","changeMPerHour":0.181},{"timestampUtc":"2026-07-14T22:30:00Z","heightM":0.38761091232299805,"phase":"rising","changeMPerHour":0.1062},{"timestampUtc":"2026-07-14T23:00:00Z","heightM":0.40030184388160706,"phase":"rising","changeMPerHour":0.0254},{"timestampUtc":"2026-07-14T23:30:00Z","heightM":0.37278151512145996,"phase":"falling","changeMPerHour":-0.055},{"timestampUtc":"2026-07-15T00:00:00Z","heightM":0.30832353234291077,"phase":"falling","changeMPerHour":-0.1289},{"timestampUtc":"2026-07-15T00:30:00Z","heightM":0.21295654773712158,"phase":"falling","changeMPerHour":-0.1907},{"timestampUtc":"2026-07-15T01:00:00Z","heightM":0.09490299969911575,"phase":"falling","changeMPerHour":-0.2361},{"timestampUtc":"2026-07-15T01:30:00Z","heightM":-0.03612757474184036,"phase":"falling","changeMPerHour":-0.2621},{"timestampUtc":"2026-07-15T02:00:00Z","heightM":-0.16970594227313995,"phase":"falling","changeMPerHour":-0.2672},{"timestampUtc":"2026-07-15T02:30:00Z","heightM":-0.29543107748031616,"phase":"falling","changeMPerHour":-0.2515},{"timestampUtc":"2026-07-15T03:00:00Z","heightM":-0.40359705686569214,"phase":"falling","changeMPerHour":-0.2163},{"timestampUtc":"2026-07-15T03:30:00Z","heightM":-0.48574304580688477,"phase":"falling","changeMPerHour":-0.1643},{"timestampUtc":"2026-07-15T04:00:00Z","heightM":-0.5350762605667114,"phase":"falling","changeMPerHour":-0.0987},{"timestampUtc":"2026-07-15T04:30:00Z","heightM":-0.5467786192893982,"phase":"falling","changeMPerHour":-0.0234},{"timestampUtc":"2026-07-15T05:00:00Z","heightM":-0.5182172656059265,"phase":"rising","changeMPerHour":0.0571},{"timestampUtc":"2026-07-15T05:30:00Z","heightM":-0.4490787088871002,"phase":"rising","changeMPerHour":0.1383},{"timestampUtc":"2026-07-15T06:00:00Z","heightM":-0.34143418073654175,"phase":"rising","changeMPerHour":0.2153},{"timestampUtc":"2026-07-15T06:30:00Z","heightM":-0.19972938299179077,"phase":"rising","changeMPerHour":0.2834},{"timestampUtc":"2026-07-15T07:00:00Z","heightM":-0.030675925314426422,"phase":"rising","changeMPerHour":0.3381},{"timestampUtc":"2026-07-15T07:30:00Z","heightM":0.1569848656654358,"phase":"rising","changeMPerHour":0.3753},{"timestampUtc":"2026-07-15T08:00:00Z","heightM":0.3528725504875183,"phase":"rising","changeMPerHour":0.3918},{"timestampUtc":"2026-07-15T08:30:00Z","heightM":0.5455237030982971,"phase":"rising","changeMPerHour":0.3853},{"timestampUtc":"2026-07-15T09:00:00Z","heightM":0.7230996489524841,"phase":"rising","changeMPerHour":0.3552},{"timestampUtc":"2026-07-15T09:30:00Z","heightM":0.8742029070854187,"phase":"rising","changeMPerHour":0.3022},{"timestampUtc":"2026-07-15T10:00:00Z","heightM":0.9887317419052124,"phase":"rising","changeMPerHour":0.2291},{"timestampUtc":"2026-07-15T10:30:00Z","heightM":1.0586847066879272,"phase":"rising","changeMPerHour":0.1399},{"timestampUtc":"2026-07-15T11:00:00Z","heightM":1.0788230895996094,"phase":"rising","changeMPerHour":0.0403},{"timestampUtc":"2026-07-15T11:30:00Z","heightM":1.0471111536026,"phase":"falling","changeMPerHour":-0.0634},{"timestampUtc":"2026-07-15T12:00:00Z","heightM":0.964881420135498,"phase":"falling","changeMPerHour":-0.1645},{"timestampUtc":"2026-07-15T12:30:00Z","heightM":0.836707592010498,"phase":"falling","changeMPerHour":-0.2563},{"timestampUtc":"2026-07-15T13:00:00Z","heightM":0.6700078845024109,"phase":"falling","changeMPerHour":-0.3334},{"timestampUtc":"2026-07-15T13:30:00Z","heightM":0.4744347035884857,"phase":"falling","changeMPerHour":-0.3911},{"timestampUtc":"2026-07-15T14:00:00Z","heightM":0.2611297070980072,"phase":"falling","changeMPerHour":-0.4266},{"timestampUtc":"2026-07-15T14:30:00Z","heightM":0.04192991554737091,"phase":"falling","changeMPerHour":-0.4384},{"timestampUtc":"2026-07-15T15:00:00Z","heightM":-0.17139600217342377,"phase":"falling","changeMPerHour":-0.4267},{"timestampUtc":"2026-07-15T15:30:00Z","heightM":-0.36782339215278625,"phase":"falling","changeMPerHour":-0.3929},{"timestampUtc":"2026-07-15T16:00:00Z","heightM":-0.5376265645027161,"phase":"falling","changeMPerHour":-0.3396},{"timestampUtc":"2026-07-15T16:30:00Z","heightM":-0.672806441783905,"phase":"falling","changeMPerHour":-0.2704},{"timestampUtc":"2026-07-15T17:00:00Z","heightM":-0.7674037218093872,"phase":"falling","changeMPerHour":-0.1892},{"timestampUtc":"2026-07-15T17:30:00Z","heightM":-0.8177179098129272,"phase":"falling","changeMPerHour":-0.1006},{"timestampUtc":"2026-07-15T18:00:00Z","heightM":-0.8224504590034485,"phase":"slack","changeMPerHour":-0.0095},{"timestampUtc":"2026-07-15T18:30:00Z","heightM":-0.7827779054641724,"phase":"rising","changeMPerHour":0.0793},{"timestampUtc":"2026-07-15T19:00:00Z","heightM":-0.7023451328277588,"phase":"rising","changeMPerHour":0.1609},{"timestampUtc":"2026-07-15T19:30:00Z","heightM":-0.5871542096138,"phase":"rising","changeMPerHour":0.2304},{"timestampUtc":"2026-07-15T20:00:00Z","heightM":-0.4453200399875641,"phase":"rising","changeMPerHour":0.2837},{"timestampUtc":"2026-07-15T20:30:00Z","heightM":-0.28666678071022034,"phase":"rising","changeMPerHour":0.3173},{"timestampUtc":"2026-07-15T21:00:00Z","heightM":-0.12215793132781982,"phase":"rising","changeMPerHour":0.329},{"timestampUtc":"2026-07-15T21:30:00Z","heightM":0.03682173043489456,"phase":"rising","changeMPerHour":0.318},{"timestampUtc":"2026-07-15T22:00:00Z","heightM":0.17928491532802582,"phase":"rising","changeMPerHour":0.2849},{"timestampUtc":"2026-07-15T22:30:00Z","heightM":0.29548755288124084,"phase":"rising","changeMPerHour":0.2324},{"timestampUtc":"2026-07-15T23:00:00Z","heightM":0.37771186232566833,"phase":"rising","changeMPerHour":0.1644},{"timestampUtc":"2026-07-15T23:30:00Z","heightM":0.4208960235118866,"phase":"rising","changeMPerHour":0.0864},{"timestampUtc":"2026-07-16T00:00:00Z","heightM":0.42303407192230225,"phase":"slack","changeMPerHour":0.0043},{"timestampUtc":"2026-07-16T00:30:00Z","heightM":0.3852989375591278,"phase":"falling","changeMPerHour":-0.0755},{"timestampUtc":"2026-07-16T01:00:00Z","heightM":0.3118779957294464,"phase":"falling","changeMPerHour":-0.1468},{"timestampUtc":"2026-07-16T01:30:00Z","heightM":0.20954984426498413,"phase":"falling","changeMPerHour":-0.2047},{"timestampUtc":"2026-07-16T02:00:00Z","heightM":0.08706304430961609,"phase":"falling","changeMPerHour":-0.245},{"timestampUtc":"2026-07-16T02:30:00Z","heightM":-0.04560248553752899,"phase":"falling","changeMPerHour":-0.2653},{"timestampUtc":"2026-07-16T03:00:00Z","heightM":-0.17800523340702057,"phase":"falling","changeMPerHour":-0.2648},{"timestampUtc":"2026-07-16T03:30:00Z","heightM":-0.2999679446220398,"phase":"falling","changeMPerHour":-0.2439},{"timestampUtc":"2026-07-16T04:00:00Z","heightM":-0.40220537781715393,"phase":"falling","changeMPerHour":-0.2045},{"timestampUtc":"2026-07-16T04:30:00Z","heightM":-0.47682687640190125,"phase":"falling","changeMPerHour":-0.1492},{"timestampUtc":"2026-07-16T05:00:00Z","heightM":-0.5177114009857178,"phase":"falling","changeMPerHour":-0.0818},{"timestampUtc":"2026-07-16T05:30:00Z","heightM":-0.5207712650299072,"phase":"slack","changeMPerHour":-0.0061},{"timestampUtc":"2026-07-16T06:00:00Z","heightM":-0.4841260313987732,"phase":"rising","changeMPerHour":0.0733},{"timestampUtc":"2026-07-16T06:30:00Z","heightM":-0.4082046151161194,"phase":"rising","changeMPerHour":0.1518},{"timestampUtc":"2026-07-16T07:00:00Z","heightM":-0.2957801818847656,"phase":"rising","changeMPerHour":0.2248},{"timestampUtc":"2026-07-16T07:30:00Z","heightM":-0.15192583203315735,"phase":"rising","changeMPerHour":0.2877},{"timestampUtc":"2026-07-16T08:00:00Z","heightM":0.016133319586515427,"phase":"rising","changeMPerHour":0.3361},{"timestampUtc":"2026-07-16T08:30:00Z","heightM":0.19930151104927063,"phase":"rising","changeMPerHour":0.3663},{"timestampUtc":"2026-07-16T09:00:00Z","heightM":0.38704943656921387,"phase":"rising","changeMPerHour":0.3755},{"timestampUtc":"2026-07-16T09:30:00Z","heightM":0.568011462688446,"phase":"rising","changeMPerHour":0.3619},{"timestampUtc":"2026-07-16T10:00:00Z","heightM":0.7307202816009521,"phase":"rising","changeMPerHour":0.3254},{"timestampUtc":"2026-07-16T10:30:00Z","heightM":0.8644272685050964,"phase":"rising","changeMPerHour":0.2674},{"timestampUtc":"2026-07-16T11:00:00Z","heightM":0.9599327445030212,"phase":"rising","changeMPerHour":0.191},{"timestampUtc":"2026-07-16T11:30:00Z","heightM":1.0103352069854736,"phase":"rising","changeMPerHour":0.1008},{"timestampUtc":"2026-07-16T12:00:00Z","heightM":1.011612057685852,"phase":"slack","changeMPerHour":0.0026},{"timestampUtc":"2026-07-16T12:30:00Z","heightM":0.9629592895507812,"phase":"falling","changeMPerHour":-0.0973},{"timestampUtc":"2026-07-16T13:00:00Z","heightM":0.8668501973152161,"phase":"falling","changeMPerHour":-0.1922},{"timestampUtc":"2026-07-16T13:30:00Z","heightM":0.7288089394569397,"phase":"falling","changeMPerHour":-0.2761},{"timestampUtc":"2026-07-16T14:00:00Z","heightM":0.5569347739219666,"phase":"falling","changeMPerHour":-0.3437},{"timestampUtc":"2026-07-16T14:30:00Z","heightM":0.36124157905578613,"phase":"falling","changeMPerHour":-0.3914},{"timestampUtc":"2026-07-16T15:00:00Z","heightM":0.15289610624313354,"phase":"falling","changeMPerHour":-0.4167},{"timestampUtc":"2026-07-16T15:30:00Z","heightM":-0.05655994266271591,"phase":"falling","changeMPerHour":-0.4189},{"timestampUtc":"2026-07-16T16:00:00Z","heightM":-0.25593188405036926,"phase":"falling","changeMPerHour":-0.3987},{"timestampUtc":"2026-07-16T16:30:00Z","heightM":-0.4349883794784546,"phase":"falling","changeMPerHour":-0.3581},{"timestampUtc":"2026-07-16T17:00:00Z","heightM":-0.5849497318267822,"phase":"falling","changeMPerHour":-0.2999},{"timestampUtc":"2026-07-16T17:30:00Z","heightM":-0.6988505125045776,"phase":"falling","changeMPerHour":-0.2278},{"timestampUtc":"2026-07-16T18:00:00Z","heightM":-0.771794319152832,"phase":"falling","changeMPerHour":-0.1459},{"timestampUtc":"2026-07-16T18:30:00Z","heightM":-0.8011242151260376,"phase":"falling","changeMPerHour":-0.0587},{"timestampUtc":"2026-07-16T19:00:00Z","heightM":-0.7865245342254639,"phase":"rising","changeMPerHour":0.0292},{"timestampUtc":"2026-07-16T19:30:00Z","heightM":-0.7300575375556946,"phase":"rising","changeMPerHour":0.1129},{"timestampUtc":"2026-07-16T20:00:00Z","heightM":-0.6361202001571655,"phase":"rising","changeMPerHour":0.1879},{"timestampUtc":"2026-07-16T20:30:00Z","heightM":-0.5112956166267395,"phase":"rising","changeMPerHour":0.2496},{"timestampUtc":"2026-07-16T21:00:00Z","heightM":-0.3640686571598053,"phase":"rising","changeMPerHour":0.2945},{"timestampUtc":"2026-07-16T21:30:00Z","heightM":-0.20438601076602936,"phase":"rising","changeMPerHour":0.3194},{"timestampUtc":"2026-07-16T22:00:00Z","heightM":-0.04305822029709816,"phase":"rising","changeMPerHour":0.3227},{"timestampUtc":"2026-07-16T22:30:00Z","heightM":0.1089692935347557,"phase":"rising","changeMPerHour":0.3041},{"timestampUtc":"2026-07-16T23:00:00Z","heightM":0.2414218783378601,"phase":"rising","changeMPerHour":0.2649},{"timestampUtc":"2026-07-16T23:30:00Z","heightM":0.34549981355667114,"phase":"rising","changeMPerHour":0.2082},{"timestampUtc":"2026-07-17T00:00:00Z","heightM":0.4145914912223816,"phase":"rising","changeMPerHour":0.1382},{"timestampUtc":"2026-07-17T00:30:00Z","heightM":0.44481006264686584,"phase":"rising","changeMPerHour":0.0604},{"timestampUtc":"2026-07-17T01:00:00Z","heightM":0.4352869987487793,"phase":"falling","changeMPerHour":-0.019},{"timestampUtc":"2026-07-17T01:30:00Z","heightM":0.38818851113319397,"phase":"falling","changeMPerHour":-0.0942},{"timestampUtc":"2026-07-17T02:00:00Z","heightM":0.30845770239830017,"phase":"falling","changeMPerHour":-0.1595},{"timestampUtc":"2026-07-17T02:30:00Z","heightM":0.2033238708972931,"phase":"falling","changeMPerHour":-0.2103},{"timestampUtc":"2026-07-17T03:00:00Z","heightM":0.08164682239294052,"phase":"falling","changeMPerHour":-0.2434},{"timestampUtc":"2026-07-17T03:30:00Z","heightM":-0.04681940749287605,"phase":"falling","changeMPerHour":-0.2569},{"timestampUtc":"2026-07-17T04:00:00Z","heightM":-0.17216095328330994,"phase":"falling","changeMPerHour":-0.2507},{"timestampUtc":"2026-07-17T04:30:00Z","heightM":-0.28496864438056946,"phase":"falling","changeMPerHour":-0.2256},{"timestampUtc":"2026-07-17T05:00:00Z","heightM":-0.3768891394138336,"phase":"falling","changeMPerHour":-0.1838},{"timestampUtc":"2026-07-17T05:30:00Z","heightM":-0.44104650616645813,"phase":"falling","changeMPerHour":-0.1283},{"timestampUtc":"2026-07-17T06:00:00Z","heightM":-0.4723414182662964,"phase":"falling","changeMPerHour":-0.0626},{"timestampUtc":"2026-07-17T06:30:00Z","heightM":-0.46764981746673584,"phase":"slack","changeMPerHour":0.0094},{"timestampUtc":"2026-07-17T07:00:00Z","heightM":-0.4259452819824219,"phase":"rising","changeMPerHour":0.0834},{"timestampUtc":"2026-07-17T07:30:00Z","heightM":-0.34836143255233765,"phase":"rising","changeMPerHour":0.1552},{"timestampUtc":"2026-07-17T08:00:00Z","heightM":-0.2381952852010727,"phase":"rising","changeMPerHour":0.2203},{"timestampUtc":"2026-07-17T08:30:00Z","heightM":-0.10083615034818649,"phase":"rising","changeMPerHour":0.2747},{"timestampUtc":"2026-07-17T09:00:00Z","heightM":0.05640699714422226,"phase":"rising","changeMPerHour":0.3145},{"timestampUtc":"2026-07-17T09:30:00Z","heightM":0.22460921108722687,"phase":"rising","changeMPerHour":0.3364},{"timestampUtc":"2026-07-17T10:00:00Z","heightM":0.39368316531181335,"phase":"rising","changeMPerHour":0.3381},{"timestampUtc":"2026-07-17T10:30:00Z","heightM":0.5529811382293701,"phase":"rising","changeMPerHour":0.3186},{"timestampUtc":"2026-07-17T11:00:00Z","heightM":0.6920161843299866,"phase":"rising","changeMPerHour":0.2781},{"timestampUtc":"2026-07-17T11:30:00Z","heightM":0.8012446761131287,"phase":"rising","changeMPerHour":0.2185},{"timestampUtc":"2026-07-17T12:00:00Z","heightM":0.8728318810462952,"phase":"rising","changeMPerHour":0.1432},{"timestampUtc":"2026-07-17T12:30:00Z","heightM":0.9013124704360962,"phase":"rising","changeMPerHour":0.057},{"timestampUtc":"2026-07-17T13:00:00Z","heightM":0.8840630650520325,"phase":"falling","changeMPerHour":-0.0345},{"timestampUtc":"2026-07-17T13:30:00Z","heightM":0.8215283155441284,"phase":"falling","changeMPerHour":-0.1251},{"timestampUtc":"2026-07-17T14:00:00Z","heightM":0.7171709537506104,"phase":"falling","changeMPerHour":-0.2087},{"timestampUtc":"2026-07-17T14:30:00Z","heightM":0.5771582126617432,"phase":"falling","changeMPerHour":-0.28},{"timestampUtc":"2026-07-17T15:00:00Z","heightM":0.4098298251628876,"phase":"falling","changeMPerHour":-0.3347},{"timestampUtc":"2026-07-17T15:30:00Z","heightM":0.2250194102525711,"phase":"falling","changeMPerHour":-0.3696},{"timestampUtc":"2026-07-17T16:00:00Z","heightM":0.03331449627876282,"phase":"falling","changeMPerHour":-0.3834},{"timestampUtc":"2026-07-17T16:30:00Z","heightM":-0.1546655148267746,"phase":"falling","changeMPerHour":-0.376},{"timestampUtc":"2026-07-17T17:00:00Z","heightM":-0.32890957593917847,"phase":"falling","changeMPerHour":-0.3485},{"timestampUtc":"2026-07-17T17:30:00Z","heightM":-0.4805358946323395,"phase":"falling","changeMPerHour":-0.3033},{"timestampUtc":"2026-07-17T18:00:00Z","heightM":-0.6021832823753357,"phase":"falling","changeMPerHour":-0.2433},{"timestampUtc":"2026-07-17T18:30:00Z","heightM":-0.6882843971252441,"phase":"falling","changeMPerHour":-0.1722},{"timestampUtc":"2026-07-17T19:00:00Z","heightM":-0.7352457642555237,"phase":"falling","changeMPerHour":-0.0939},{"timestampUtc":"2026-07-17T19:30:00Z","heightM":-0.7415595054626465,"phase":"falling","changeMPerHour":-0.0126},{"timestampUtc":"2026-07-17T20:00:00Z","heightM":-0.7078618407249451,"phase":"rising","changeMPerHour":0.0674},{"timestampUtc":"2026-07-17T20:30:00Z","heightM":-0.6369370222091675,"phase":"rising","changeMPerHour":0.1418},{"timestampUtc":"2026-07-17T21:00:00Z","heightM":-0.5336496233940125,"phase":"rising","changeMPerHour":0.2066},{"timestampUtc":"2026-07-17T21:30:00Z","heightM":-0.4047754406929016,"phase":"rising","changeMPerHour":0.2577},{"timestampUtc":"2026-07-17T22:00:00Z","heightM":-0.2587027847766876,"phase":"rising","changeMPerHour":0.2921},{"timestampUtc":"2026-07-17T22:30:00Z","heightM":-0.10498547554016113,"phase":"rising","changeMPerHour":0.3074},{"timestampUtc":"2026-07-17T23:00:00Z","heightM":0.04624805599451065,"phase":"rising","changeMPerHour":0.3025},{"timestampUtc":"2026-07-17T23:30:00Z","heightM":0.1849977672100067,"phase":"rising","changeMPerHour":0.2775},{"timestampUtc":"2026-07-18T00:00:00Z","heightM":0.30214762687683105,"phase":"rising","changeMPerHour":0.2343},{"timestampUtc":"2026-07-18T00:30:00Z","heightM":0.39019501209259033,"phase":"rising","changeMPerHour":0.1761},{"timestampUtc":"2026-07-18T01:00:00Z","heightM":0.44386714696884155,"phase":"rising","changeMPerHour":0.1073},{"timestampUtc":"2026-07-18T01:30:00Z","heightM":0.4605473279953003,"phase":"rising","changeMPerHour":0.0334},{"timestampUtc":"2026-07-18T02:00:00Z","heightM":0.44045618176460266,"phase":"falling","changeMPerHour":-0.0402},{"timestampUtc":"2026-07-18T02:30:00Z","heightM":0.38656726479530334,"phase":"falling","changeMPerHour":-0.1078},{"timestampUtc":"2026-07-18T03:00:00Z","heightM":0.3042735755443573,"phase":"falling","changeMPerHour":-0.1646},{"timestampUtc":"2026-07-18T03:30:00Z","heightM":0.20085610449314117,"phase":"falling","changeMPerHour":-0.2068},{"timestampUtc":"2026-07-18T04:00:00Z","heightM":0.08482780307531357,"phase":"falling","changeMPerHour":-0.2321},{"timestampUtc":"2026-07-18T04:30:00Z","heightM":-0.03476333990693092,"phase":"falling","changeMPerHour":-0.2392},{"timestampUtc":"2026-07-18T05:00:00Z","heightM":-0.14899607002735138,"phase":"falling","changeMPerHour":-0.2285},{"timestampUtc":"2026-07-18T05:30:00Z","heightM":-0.24964511394500732,"phase":"falling","changeMPerHour":-0.2013},{"timestampUtc":"2026-07-18T06:00:00Z","heightM":-0.32962721586227417,"phase":"falling","changeMPerHour":-0.16},{"timestampUtc":"2026-07-18T06:30:00Z","heightM":-0.38332024216651917,"phase":"falling","changeMPerHour":-0.1074},{"timestampUtc":"2026-07-18T07:00:00Z","heightM":-0.4067724049091339,"phase":"falling","changeMPerHour":-0.0469},{"timestampUtc":"2026-07-18T07:30:00Z","heightM":-0.3978296220302582,"phase":"rising","changeMPerHour":0.0179},{"timestampUtc":"2026-07-18T08:00:00Z","heightM":-0.3562066853046417,"phase":"rising","changeMPerHour":0.0832},{"timestampUtc":"2026-07-18T08:30:00Z","heightM":-0.2835164964199066,"phase":"rising","changeMPerHour":0.1454},{"timestampUtc":"2026-07-18T09:00:00Z","heightM":-0.183254674077034,"phase":"rising","changeMPerHour":0.2005},{"timestampUtc":"2026-07-18T09:30:00Z","heightM":-0.06071919947862625,"phase":"rising","changeMPerHour":0.2451},{"timestampUtc":"2026-07-18T10:00:00Z","heightM":0.07716453075408936,"phase":"rising","changeMPerHour":0.2758},{"timestampUtc":"2026-07-18T10:30:00Z","heightM":0.22214286029338837,"phase":"rising","changeMPerHour":0.29},{"timestampUtc":"2026-07-18T11:00:00Z","heightM":0.36507371068000793,"phase":"rising","changeMPerHour":0.2859},{"timestampUtc":"2026-07-18T11:30:00Z","heightM":0.4965011179447174,"phase":"rising","changeMPerHour":0.2629},{"timestampUtc":"2026-07-18T12:00:00Z","heightM":0.6073301434516907,"phase":"rising","changeMPerHour":0.2217},{"timestampUtc":"2026-07-18T12:30:00Z","heightM":0.6895415782928467,"phase":"rising","changeMPerHour":0.1644},{"timestampUtc":"2026-07-18T13:00:00Z","heightM":0.736868143081665,"phase":"rising","changeMPerHour":0.0947},{"timestampUtc":"2026-07-18T13:30:00Z","heightM":0.7453475594520569,"phase":"rising","changeMPerHour":0.017},{"timestampUtc":"2026-07-18T14:00:00Z","heightM":0.7136809825897217,"phase":"falling","changeMPerHour":-0.0633},{"timestampUtc":"2026-07-18T14:30:00Z","heightM":0.6433473229408264,"phase":"falling","changeMPerHour":-0.1407},{"timestampUtc":"2026-07-18T15:00:00Z","heightM":0.5384607315063477,"phase":"falling","changeMPerHour":-0.2098},{"timestampUtc":"2026-07-18T15:30:00Z","heightM":0.4053937494754791,"phase":"falling","changeMPerHour":-0.2661},{"timestampUtc":"2026-07-18T16:00:00Z","heightM":0.2522210478782654,"phase":"falling","changeMPerHour":-0.3063},{"timestampUtc":"2026-07-18T16:30:00Z","heightM":0.08806011825799942,"phase":"falling","changeMPerHour":-0.3283},{"timestampUtc":"2026-07-18T17:00:00Z","heightM":-0.07761009782552719,"phase":"falling","changeMPerHour":-0.3313},{"timestampUtc":"2026-07-18T17:30:00Z","heightM":-0.23557965457439423,"phase":"falling","changeMPerHour":-0.3159},{"timestampUtc":"2026-07-18T18:00:00Z","heightM":-0.37743642926216125,"phase":"falling","changeMPerHour":-0.2837},{"timestampUtc":"2026-07-18T18:30:00Z","heightM":-0.4959687292575836,"phase":"falling","changeMPerHour":-0.2371},{"timestampUtc":"2026-07-18T19:00:00Z","heightM":-0.5854446291923523,"phase":"falling","changeMPerHour":-0.179},{"timestampUtc":"2026-07-18T19:30:00Z","heightM":-0.6417895555496216,"phase":"falling","changeMPerHour":-0.1127},{"timestampUtc":"2026-07-18T20:00:00Z","heightM":-0.6626916527748108,"phase":"falling","changeMPerHour":-0.0418},{"timestampUtc":"2026-07-18T20:30:00Z","heightM":-0.6476621627807617,"phase":"rising","changeMPerHour":0.0301},{"timestampUtc":"2026-07-18T21:00:00Z","heightM":-0.5980623364448547,"phase":"rising","changeMPerHour":0.0992},{"timestampUtc":"2026-07-18T21:30:00Z","heightM":-0.5170914530754089,"phase":"rising","changeMPerHour":0.1619},{"timestampUtc":"2026-07-18T22:00:00Z","heightM":-0.40971386432647705,"phase":"rising","changeMPerHour":0.2148},{"timestampUtc":"2026-07-18T22:30:00Z","heightM":-0.28249305486679077,"phase":"rising","changeMPerHour":0.2544},{"timestampUtc":"2026-07-18T23:00:00Z","heightM":-0.14330288767814636,"phase":"rising","changeMPerHour":0.2784},{"timestampUtc":"2026-07-18T23:30:00Z","heightM":-0.000900647253729403,"phase":"rising","changeMPerHour":0.2848},{"timestampUtc":"2026-07-19T00:00:00Z","heightM":0.13562999665737152,"phase":"rising","changeMPerHour":0.2731},{"timestampUtc":"2026-07-19T00:30:00Z","heightM":0.2575302720069885,"phase":"rising","changeMPerHour":0.2438},{"timestampUtc":"2026-07-19T01:00:00Z","heightM":0.3570499122142792,"phase":"rising","changeMPerHour":0.199},{"timestampUtc":"2026-07-19T01:30:00Z","heightM":0.428085058927536,"phase":"rising","changeMPerHour":0.1421},{"timestampUtc":"2026-07-19T02:00:00Z","heightM":0.46668949723243713,"phase":"rising","changeMPerHour":0.0772},{"timestampUtc":"2026-07-19T02:30:00Z","heightM":0.471390962600708,"phase":"slack","changeMPerHour":0.0094}],"events":[{"type":"HIGH","timestampUtc":"2026-07-12T08:30:00Z","heightM":0.9441043138504028},{"type":"LOW","timestampUtc":"2026-07-12T15:00:00Z","heightM":-0.6659493446350098},{"type":"HIGH","timestampUtc":"2026-07-12T21:00:00Z","heightM":0.3276238441467285},{"type":"LOW","timestampUtc":"2026-07-13T02:30:00Z","heightM":-0.5233868360519409},{"type":"HIGH","timestampUtc":"2026-07-13T09:00:00Z","heightM":1.0287349224090576},{"type":"LOW","timestampUtc":"2026-07-13T16:00:00Z","heightM":-0.755944013595581},{"type":"HIGH","timestampUtc":"2026-07-13T22:00:00Z","heightM":0.36695781350135803},{"type":"LOW","timestampUtc":"2026-07-14T03:30:00Z","heightM":-0.5448406338691711},{"type":"HIGH","timestampUtc":"2026-07-14T10:00:00Z","heightM":1.0816965103149414},{"type":"LOW","timestampUtc":"2026-07-14T17:00:00Z","heightM":-0.8112548589706421},{"type":"HIGH","timestampUtc":"2026-07-14T23:00:00Z","heightM":0.40030184388160706},{"type":"LOW","timestampUtc":"2026-07-15T04:30:00Z","heightM":-0.5467786192893982},{"type":"HIGH","timestampUtc":"2026-07-15T11:00:00Z","heightM":1.0788230895996094},{"type":"LOW","timestampUtc":"2026-07-15T18:00:00Z","heightM":-0.8224504590034485},{"type":"HIGH","timestampUtc":"2026-07-16T00:00:00Z","heightM":0.42303407192230225},{"type":"LOW","timestampUtc":"2026-07-16T05:30:00Z","heightM":-0.5207712650299072},{"type":"HIGH","timestampUtc":"2026-07-16T12:00:00Z","heightM":1.011612057685852},{"type":"LOW","timestampUtc":"2026-07-16T18:30:00Z","heightM":-0.8011242151260376},{"type":"HIGH","timestampUtc":"2026-07-17T00:30:00Z","heightM":0.44481006264686584},{"type":"LOW","timestampUtc":"2026-07-17T06:00:00Z","heightM":-0.4723414182662964},{"type":"HIGH","timestampUtc":"2026-07-17T12:30:00Z","heightM":0.9013124704360962},{"type":"LOW","timestampUtc":"2026-07-17T19:30:00Z","heightM":-0.7415595054626465},{"type":"HIGH","timestampUtc":"2026-07-18T01:30:00Z","heightM":0.4605473279953003},{"type":"LOW","timestampUtc":"2026-07-18T07:00:00Z","heightM":-0.4067724049091339},{"type":"HIGH","timestampUtc":"2026-07-18T13:30:00Z","heightM":0.7453475594520569},{"type":"LOW","timestampUtc":"2026-07-18T20:00:00Z","heightM":-0.6626916527748108}],"dailyRanges":[{"dateUtc":"2026-07-12","rangeM":1.61,"highM":0.9441043138504028,"lowM":-0.6659493446350098},{"dateUtc":"2026-07-13","rangeM":1.785,"highM":1.0287349224090576,"lowM":-0.755944013595581},{"dateUtc":"2026-07-14","rangeM":1.893,"highM":1.0816965103149414,"lowM":-0.8112548589706421},{"dateUtc":"2026-07-15","rangeM":1.901,"highM":1.0788230895996094,"lowM":-0.8224504590034485},{"dateUtc":"2026-07-16","rangeM":1.813,"highM":1.011612057685852,"lowM":-0.8011242151260376},{"dateUtc":"2026-07-17","rangeM":1.643,"highM":0.9013124704360962,"lowM":-0.7415595054626465},{"dateUtc":"2026-07-18","rangeM":1.408,"highM":0.7453475594520569,"lowM":-0.6626916527748108},{"dateUtc":"2026-07-19","rangeM":0.336,"highM":0.471390962600708,"lowM":0.13562999665737152}]}